Metadata-Version: 2.1
Name: helloasso-apiv5
Version: 1.0.0
Summary: Python wrapper for Helloasso APIV5
Home-page: https://github.com/HelloAsso/HaApiV5
Author: Helloasso
Author-email: api.support@helloasso.org
Maintainer: Helloasso
License: MIT License
Platform: UNKNOWN
Requires-Python: >=3.6
License-File: LICENSE
